{
  "displayName": "Git 快速合并",
  "description": "快速合并Git分支到指定分支的VSCode插件",
  "config.title": "Git 快速合并",
  "config.branches.description": "可选的目标分支列表 - 合并时可以选择的目标分支",
  "config.branches.items.description": "分支名称",
  "config.skipStaleWorktreeCheck.description": "是否跳过启动时检查历史残留的 worktree 目录",
  "config.remoteRepoName.description": "远程仓库名称，默认为 origin",
  "config.mergePresets.description": "预设的合并组合，支持一键多分支合并",
  "config.mergePresets.items.name.description": "此合并预设的显示名称",
  "config.mergePresets.items.branches.description": "此预设包含的目标分支列表",
  "command.quickMergeTo.title": "快速合并",
  "command.cleanupStaleWorktrees.title": "清理历史残留的 Worktrees"
}


